madflow/__init__.py
madflow/config.py
madflow/lhe_writer.py
madflow/parameters.py
madflow/phasespace.py
madflow/py.py
madflow/utilities.py
madflow/wavefunctions_flow.py
madflow/scripts/__init__.py
madflow/scripts/madflow_exec.py
madflow/scripts/py.py
madflow/tests/__init__.py
madflow/tests/mockup_debug_me.py
madflow/tests/test_integration.py
madflow/tests/test_ps.py
madflow-0.9.dist-info/LICENSE
madflow-0.9.dist-info/METADATA
madflow-0.9.dist-info/WHEEL
madflow-0.9.dist-info/entry_points.txt
madflow-0.9.dist-info/top_level.txt
madflow-0.9.dist-info/RECORD
