Metadata-Version: 2.1
Name: madflow
Version: 0.9
Summary: Package for GPU fixed order calculations
Home-page: https://github.com/N3PDF/madflow/
Author: S. Carrazza, J. Cruz-Martinez, M. Rossi, M. Zaro
Author-email: n3pdf@lairen.eu
License: Apache 2
Platform: UNKNOWN
Classifier: Operating System :: Unix
Classifier: Programming Language :: Python
Classifier: Programming Language :: Python :: 3
Classifier: Topic :: Scientific/Engineering
Classifier: Topic :: Scientific/Engineering :: Physics
Requires-Python: >=3.6
License-File: LICENSE
Requires-Dist: vegasflow
Requires-Dist: pdfflow
Requires-Dist: requests
Provides-Extra: amd
Requires-Dist: tensorflow-rocm ; extra == 'amd'
Provides-Extra: docs
Requires-Dist: sphinx-rtd-theme ; extra == 'docs'
Requires-Dist: recommonmark ; extra == 'docs'
Requires-Dist: sphinxcontrib-bibtex ; extra == 'docs'
